Metadata-Version: 2.1
Name: phil-loc
Version: 0.6.2
Summary: Django library package for Locations/Addresses in the Philippines based on Philippine Standard Geographic Code(PSGC)
Home-page: https://github.com/delletran/phil_loc
Author: Rodel Letran
Author-email: delioletran@gmail.com
License: MIT License
Classifier: Environment :: Web Environment
Classifier: Framework :: Django
Classifier: Framework :: Django :: 5.1
Classifier: Intended Audience :: Developers
Classifier: License :: OSI Approved :: MIT License
Classifier: Operating System :: OS Independent
Classifier: Programming Language :: Python
Classifier: Programming Language :: Python :: 3
Classifier: Programming Language :: Python :: 3.7
Classifier: Programming Language :: Python :: 3.8
Classifier: Programming Language :: Python :: 3.9
Classifier: Programming Language :: Python :: 3.10
Classifier: Programming Language :: Python :: 3.11
Classifier: Topic :: Internet :: WWW/HTTP
Classifier: Topic :: Internet :: WWW/HTTP :: Dynamic Content
License-File: LICENSE
Requires-Dist: django>=5.1
Requires-Dist: djangorestframework>=3.15.2
